LICENSE
MANIFEST.in
README.rst
requirements.txt
setup.cfg
setup.py
baseball_scraper/__init__.py
baseball_scraper/baseball_reference.py
baseball_scraper/batting_leaders.py
baseball_scraper/espn.py
baseball_scraper/fangraphs.py
baseball_scraper/lahman.py
baseball_scraper/league_batting_stats.py
baseball_scraper/league_pitching_stats.py
baseball_scraper/pitching_leaders.py
baseball_scraper/playerid_lookup.py
baseball_scraper/retrosheet.py
baseball_scraper/sample.fangraphs.hitter_leaderboard.csv
baseball_scraper/sample.fangraphs.pitcher_leaderboard.csv
baseball_scraper/selenium_helper.py
baseball_scraper/standings.py
baseball_scraper/statcast.py
baseball_scraper/statcast_batter.py
baseball_scraper/statcast_pitcher.py
baseball_scraper/team_batting.py
baseball_scraper/team_pitching.py
baseball_scraper/utils.py
baseball_scraper.egg-info/PKG-INFO
baseball_scraper.egg-info/SOURCES.txt
baseball_scraper.egg-info/dependency_links.txt
baseball_scraper.egg-info/requires.txt
baseball_scraper.egg-info/top_level.txt