Metadata-Version: 1.1
Name: baseball-scraper
Version: 0.4.9
Summary: Retrieve baseball data in Python
Home-page: https://github.com/spilchen/baseball_scraper
Author: Matt Spilchen
Author-email: matt.spilchen@gmail.com
License: MIT
Keywords: baseball sabermetrics data statistics statcast web scraping
Platform: UNKNOWN
Classifier: Development Status :: 4 - Beta
Classifier: Intended Audience :: Developers
Classifier: Topic :: Software Development :: Libraries
Classifier: License :: OSI Approved :: MIT License
Classifier: Programming Language :: Python :: 3
Classifier: Programming Language :: Python :: 3.3
Classifier: Programming Language :: Python :: 3.4
Classifier: Programming Language :: Python :: 3.5
Classifier: Programming Language :: Python :: 3.6
